{"cameraMode":{"drawMode":0,"name":"Shaded","section":"Shading Mode"},"sceneLighting":true,"audioPlay":false,"sceneViewState":{"showFog":true,"showMaterialUpdate":false,"showSkybox":true,"showFlares":true,"showImageEffects":true,"showParticleSystems":true},"in2DMode":false,"pivot":{"x":-10.074557304382325,"y":1.8560371398925782,"z":2.8988850116729738},"rotation":{"x":0.1133265569806099,"y":0.7389327883720398,"z":0.12850980460643769,"w":-0.6516305804252625},"size":6.307395935058594,"orthographic":false}